eqdata_generator/__init__.py
eqdata_generator/cli.py
eqdata_generator-0.0.1.dist-info/METADATA
eqdata_generator-0.0.1.dist-info/WHEEL
eqdata_generator-0.0.1.dist-info/entry_points.txt
eqdata_generator-0.0.1.dist-info/top_level.txt
eqdata_generator-0.0.1.dist-info/RECORD
